boolpriori/__init__.py
boolpriori/estimators.py
boolpriori-0.0.1.dist-info/LICENSE
boolpriori-0.0.1.dist-info/METADATA
boolpriori-0.0.1.dist-info/WHEEL
boolpriori-0.0.1.dist-info/top_level.txt
boolpriori-0.0.1.dist-info/RECORD
